{
    "key": "group_5896fb54217d7",
    "title": "Module \u2013 Text Zweispaltig",
    "fields": [
        {
            "tabs": "all",
            "toolbar": "full",
            "media_upload": 1,
            "default_value": "",
            "delay": 0,
            "key": "field_5896fb54286df",
            "label": "Linke Spalte",
            "name": "text_left",
            "type": "wysiwyg",
            "instructions": "",
            "required": 0,
            "conditional_logic": 0,
            "wrapper": {
                "width": "",
                "class": "",
                "id": ""
            }
        },
        {
            "tabs": "all",
            "toolbar": "full",
            "media_upload": 1,
            "default_value": "",
            "delay": 0,
            "key": "field_5896fb5d8c6b6",
            "label": "Rechte Spalte",
            "name": "text_right",
            "type": "wysiwyg",
            "instructions": "",
            "required": 0,
            "conditional_logic": 0,
            "wrapper": {
                "width": "",
                "class": "",
                "id": ""
            }
        }
    ],
    "location": [
        [
            {
                "param": "post_type",
                "operator": "==",
                "value": "post"
            }
        ]
    ],
    "menu_order": 0,
    "position": "normal",
    "style": "default",
    "label_placement": "top",
    "instruction_placement": "label",
    "hide_on_screen": "",
    "active": 0,
    "description": "",
    "modified": 1486293833
}